design.sv
module mux_2x1(
  input i0, i1,
  input s,
  output y
);
  
  assign y = s?i1:i0;
  
endmodule

testbench.sv
module mux_2x1_tb();
  
  reg i0, i1, s;
  wire y;
  
    mux_2x1 dut(
      .i0(i0),
      .i1(i1),
      .s(s),
      .y(y)
    );
	
  initial begin 
    
     $dumpfile("dump.vcd");
  	 $dumpvars;  
//   		i0 = 0; i1 = 0; s = 0;  // 000
//     #10 i0 = 0; i1 = 0; s = 1;  // 001
//     #10 i0 = 0; i1 = 1; s = 0;  // 010
//     #10 i0 = 0; i1 = 1; s = 1;  // 011
//     #10 i0 = 1; i1 = 0; s = 0;  // 100
//     #10 i0 = 1; i1 = 0; s = 1;  // 101
//     #10 i0 = 1; i1 = 1; s = 0;  // 110
//     #10 i0 = 1; i1 = 1; s = 1;  // 111
//     #10 $finish();
    
    repeat(15) begin
    i0= $random; i1=$random; s=$random;
    #10;
    end
  end
  
endmodule

dump.vcd
$date
Wed Jul  2 15:36:24 2025
$end
$version
Riviera-PRO Version 2023.04.112.8911
$end
$timescale
1 ns
$end

$scope module mux_2x1_tb $end
$var wire 1 ! y $end
$var reg 1 " i0 $end
$var reg 1 # i1 $end
$var reg 1 $ s $end

$scope module dut $end
$var wire 1 % i0 $end
$var wire 1 & i1 $end
$var wire 1 ' s $end
$var wire 1 ! y $end
$upscope $end

$upscope $end

$enddefinitions $end
$dumpvars
1!
0"
1#
1$
0%
1&
1'
$end
#10
1"
1%
#20
0#
0&
0!
#50
0"
1#
0$
0'
1&
0%
#60
1"
1%
1!
#70
0#
0&
#80
0"
1#
1&
0%
0!
#90
1"
1$
1'
1%
1!
#100
0#
0$
0'
0&
#110
0"
1$
1'
0%
0!
#120
1#
1&
1!
#130
1"
1%
#140
0"
0#
0&
0%
0!
